endly/__init__.py
endly/app.py
endly/decorators.py
endly/errors.py
endly/json.py
endly/logging.py
endly/middleware.py
endly/router.py
endly/static.py
endly-0.1.1.dist-info/METADATA
endly-0.1.1.dist-info/WHEEL
endly-0.1.1.dist-info/top_level.txt
endly-0.1.1.dist-info/RECORD
