Metadata-Version: 2.2
Name: endly
Version: 0.1.1
Summary: A lightweight Python web framework for building fast and scalable backend applications
Home-page: https://github.com/ishanoshada/endly
Author: Ishan Oshada
Author-email: ishan.kodithuwakku.offical@gmail.com
Project-URL: Bug Tracker, https://github.com/ishanoshada/endly/issues
Project-URL: Documentation, https://github.com/ishanoshada/endly#readme
Project-URL: Source Code, https://github.com/ishanoshada/endly
Keywords: web framework,backend,seo,web development,api,rest,http,wsgi,lightweight,fast,scalable
Classifier: Development Status :: 3 - Alpha
Classifier: Intended Audience :: Developers
Classifier: License :: OSI Approved :: MIT License
Classifier: Operating System :: OS Independent
Classifier: Programming Language :: Python :: 3
Classifier: Programming Language :: Python :: 3.7
Classifier: Programming Language :: Python :: 3.8
Classifier: Programming Language :: Python :: 3.9
Classifier: Programming Language :: Python :: 3.10
Classifier: Topic :: Internet :: WWW/HTTP :: Dynamic Content
Classifier: Topic :: Software Development :: Libraries :: Application Frameworks
Classifier: Topic :: Internet :: WWW/HTTP :: WSGI
Classifier: Topic :: Internet :: WWW/HTTP :: Site Management
Classifier: Topic :: Internet :: WWW/HTTP :: Site Management :: Link Checking
Dynamic: author
Dynamic: author-email
Dynamic: classifier
Dynamic: description
Dynamic: description-content-type
Dynamic: home-page
Dynamic: keywords
Dynamic: project-url
Dynamic: summary
